[{"cell_name": "LHON", "total pmids collected": 119}, {"cell_name": "MELAS", "total pmids collected": 123}, {"cell_name": "ADOA", "total pmids collected": 208}, {"cell_name": "Leigh", "total pmids collected": 406}, {"cell_name": "MERRF", "total pmids collected": 46}, {"cell_name": "KSS", "total pmids collected": 80}, {"cell_name": "Alpers", "total pmids collected": 261}, {"cell_name": "LBSL", "total pmids collected": 38}, {"cell_name": "PDD", "total pmids collected": 155}, {"cell_name": "PEO", "total pmids collected": 169}, {"cell_name": "MS", "total pmids collected": 2278}, {"cell_name": "Parkin", "total pmids collected": 5799}, {"cell_name": "ALS", "total pmids collected": 4026}, {"cell_name": "AD", "total pmids collected": 5979}, {"cell_name": "Epil", "total pmids collected": 3763}, {"cell_name": "Schiz", "total pmids collected": 3554}, {"cell_name": "FA", "total pmids collected": 938}, {"cell_name": "HSP", "total pmids collected": 215}, {"cell_name": "WD", "total pmids collected": 179}, {"cell_name": "LHON", "total entities collected": 71}, {"cell_name": "MELAS", "total entities collected": 73}, {"cell_name": "ADOA", "total entities collected": 45}, {"cell_name": "Leigh", "total entities collected": 163}, {"cell_name": "MERRF", "total entities collected": 40}, {"cell_name": "KSS", "total entities collected": 77}, {"cell_name": "Alpers", "total entities collected": 43}, {"cell_name": "LBSL", "total entities collected": 20}, {"cell_name": "PDD", "total entities collected": 42}, {"cell_name": "PEO", "total entities collected": 49}, {"cell_name": "MS", "total entities collected": 281}, {"cell_name": "Parkin", "total entities collected": 364}, {"cell_name": "ALS", "total entities collected": 244}, {"cell_name": "AD", "total entities collected": 433}, {"cell_name": "Epil", "total entities collected": 371}, {"cell_name": "Schiz", "total entities collected": 327}, {"cell_name": "FA", "total entities collected": 116}, {"cell_name": "HSP", "total entities collected": 78}, {"cell_name": "WD", "total entities collected": 79}]